cmtg/__init__.py
cmtg/__main__.py
cmtg/cmtg.py
cmtg/resources/__init__.py
cmtg/resources/eclipse.clr
cmtg/resources/flat.clr
cmtg/resources/macos.clr
cmtg/resources/mirc.clr
cmtg/resources/pal.bash
cmtg/resources/pal.sh
cmtg/resources/powershell6.clr
cmtg/resources/putty.clr
cmtg/resources/simple.sublime-color-scheme
cmtg/resources/ubuntu.clr
cmtg/resources/vga.clr
cmtg/resources/vscode.clr
cmtg/resources/win10.clr
cmtg/resources/winxp.clr
cmtg/resources/xterm.Xresources
cmtg/resources/xterm.clr
cmtg-1.0.1.dist-info/METADATA
cmtg-1.0.1.dist-info/WHEEL
cmtg-1.0.1.dist-info/entry_points.txt
cmtg-1.0.1.dist-info/licenses/LICENSE
cmtg-1.0.1.dist-info/RECORD
