Metadata-Version: 2.1
Name: cmtg
Version: 1.0.1
Summary: A utility for generating matching color themes
Project-URL: Homepage, https://github.com/kcghost/cmtg
Project-URL: Bug Tracker, https://github.com/kcghost/cmtg/issues
Author-email: Casey Fitzpatrick <kcghost@gmail.com>
License-File: LICENSE
Classifier: Environment :: Console
Classifier: License :: OSI Approved :: MIT License
Classifier: Operating System :: OS Independent
Classifier: Programming Language :: Python :: 3
Requires-Python: >=3.7
Requires-Dist: colormath
Requires-Dist: networkx
Requires-Dist: numpy
Requires-Dist: scipy
